PyWomboAPI/__init__.py
PyWomboAPI/generation.py
PyWomboAPI/init.py
PyWomboAPI/logger.py
PyWomboAPI/main.py
PyWomboAPI/models.py
PyWomboAPI/statics.py
PyWomboAPI-0.1.0.dist-info/LICENSE
PyWomboAPI-0.1.0.dist-info/METADATA
PyWomboAPI-0.1.0.dist-info/WHEEL
PyWomboAPI-0.1.0.dist-info/top_level.txt
PyWomboAPI-0.1.0.dist-info/RECORD
