Metadata-Version: 2.1
Name: PyWomboAPI
Version: 0.1.0
Summary: An unofficial Python library for generating images using Wombo.ai
Home-page: https://github.com/CodeSyncio/PyWomboAPI
Author: CodeSyncio
Classifier: Programming Language :: Python :: 3
Classifier: License :: OSI Approved :: MIT License
Classifier: Operating System :: OS Independent
Requires-Python: >=3.6
License-File: LICENSE
Requires-Dist: requests
Requires-Dist: lxml
Requires-Dist: aiohttp
